<?xml version='1.0'?>
<PluginConfig>
	<Field id='showTimer' type='checkbox' defaultValue='true'>
		<Label>Show Timer:</Label>
		<Description>Show time remaining in the Indigo client.</Description>
	</Field>
	<Field id='debugSeparator' type='separator' />
	<Field id='showDebugInfo' type='checkbox' defaultValue='false'>
		<Label>Enable debuging:</Label>
	</Field>
	<Field id='verboseDebug' type='checkbox' defaultValue='false' visibleBindingId='showDebugInfo'  visibleBindingValue='true'>
		<Label>Verbose debuging:</Label>
	</Field>
</PluginConfig>
